classroom/__init__.py
classroom/py.typed
classroom-0.0.0.dev0.dist-info/LICENSE
classroom-0.0.0.dev0.dist-info/METADATA
classroom-0.0.0.dev0.dist-info/WHEEL
classroom-0.0.0.dev0.dist-info/top_level.txt
classroom-0.0.0.dev0.dist-info/RECORD
