Metadata-Version: 2.1
Name: classroom
Version: 0.0.0.dev0
Summary: Teaching support for computational science courses.
Author: physicscore contributors
License: BSD 3-Clause License
Project-URL: Bug Tracker, https://github.com/physicscore/classroom/issues
Project-URL: Source, https://github.com/physicscore/classroom
Classifier: Intended Audience :: Science/Research
Classifier: License :: OSI Approved :: BSD License
Classifier: Natural Language :: English
Classifier: Operating System :: OS Independent
Classifier: Programming Language :: Python :: 3
Classifier: Programming Language :: Python :: 3 :: Only
Classifier: Programming Language :: Python :: 3.10
Classifier: Programming Language :: Python :: 3.11
Classifier: Topic :: Scientific/Engineering
Classifier: Typing :: Typed
Requires-Python: >=3.10
License-File: LICENSE
